lindh/jsonobject/__init__.py
lindh/jsonobject/noschema.py
lindh/jsonobject/schema.py
lindh/jsonobject/types.py
lindh_jsonobject-2023.2.dist-info/LICENSE
lindh_jsonobject-2023.2.dist-info/METADATA
lindh_jsonobject-2023.2.dist-info/WHEEL
lindh_jsonobject-2023.2.dist-info/top_level.txt
lindh_jsonobject-2023.2.dist-info/RECORD
