Metadata-Version: 2.1
Name: lindh-jsonobject
Version: 2023.2
Summary: Dynamic and static layer JSON serialization and deserializion of python objects
Author-email: Johan Egneblad <johan@egneblad.se>
License: MIT
Project-URL: Homepage, https://github.com/eblade/jsonobject
Project-URL: Bug Tracker, https://github.com/eblade/jsonobject/issues
Project-URL: Repository, https://github.com/eblade/jsonobject.git
Classifier: Development Status :: 6 - Mature
Classifier: Programming Language :: Python :: 3
Classifier: Operating System :: OS Independent
Classifier: Topic :: File Formats :: JSON
Requires-Python: >=3.7.1
License-File: LICENSE
Provides-Extra: release
Requires-Dist: build ; extra == 'release'
Requires-Dist: twine ; extra == 'release'
Provides-Extra: test
Requires-Dist: pytest-pep8 ; extra == 'test'
Requires-Dist: pytest-flakes ; extra == 'test'
Requires-Dist: rstcheck ; extra == 'test'
Requires-Dist: pytest-cov ; extra == 'test'
